icq/__init__.py
icq/bot.py
icq/constant.py
icq/dispatcher.py
icq/event.py
icq/filter.py
icq/handler.py
icq/util.py
python_icq_bot-0.0.19.dist-info/LICENSE
python_icq_bot-0.0.19.dist-info/METADATA
python_icq_bot-0.0.19.dist-info/WHEEL
python_icq_bot-0.0.19.dist-info/top_level.txt
python_icq_bot-0.0.19.dist-info/RECORD
