Metadata-Version: 2.1
Name: python-icq-bot
Version: 0.0.19
Summary: Pure Python interface for ICQ Bot API. Bot cookbook for Humans.
Home-page: https://github.com/icq-bot/python-icq-bot
Author: ICQ LLC (Mail.Ru Group)
Author-email: support@icq.com
License: MIT
Keywords: python icq bot api
Platform: UNKNOWN
Classifier: Development Status :: 4 - Beta
Classifier: Intended Audience :: Developers
Classifier: Topic :: Software Development :: Libraries :: Python Modules
Classifier: Topic :: Communications :: Chat
Classifier: Topic :: Internet
Classifier: License :: OSI Approved :: MIT License
Classifier: Programming Language :: Python :: 2
Classifier: Programming Language :: Python :: 2.7
Classifier: Programming Language :: Python :: 3
Classifier: Programming Language :: Python :: 3.4
Classifier: Programming Language :: Python :: 3.5
Classifier: Programming Language :: Python :: 3.6
Classifier: Programming Language :: Python :: 3.7
Classifier: Operating System :: OS Independent
Requires-Python: >= 2.7, != 3.0.*, != 3.1.*, != 3.2.*, != 3.3.*
Requires-Dist: cached-property (>=1.4.2)
Requires-Dist: expiringdict (>=1.1.4)
Requires-Dist: monotonic (>=1.5)
Requires-Dist: python-baseconv (>=1.2.1)
Requires-Dist: requests (>=2.18.4)
Requires-Dist: six (>=1.11.0)
Requires-Dist: enum34 (>=1.1.6) ; python_version < "3.4"
